onetjobsInf/OnetWebService.py
onetjobsInf/__init__.py
onetjobsInf/bfs_abilities_search.py
onetjobsInf/bfs_job_abilities_graph.py
onetjobsInf/bfs_job_knowledge_graph.py
onetjobsInf/bfs_job_skills_graph.py
onetjobsInf/bfs_knowledge_search.py
onetjobsInf/bfs_skills_search.py
onetjobsInf/onet_credentials.py
onetjobsInf/onet_keyword_search.py
onetjobsInf/pca_request_data.py
onetjobsInf/pca_run.py
onetjobsInf/pca_scaling.py
onetjobsInf/vis_app.py
onetjobsInf/vis_call_elements.py
onetjobsInf/vis_call_labels.py
onetjobsInf/vis_download_files.py
onetjobsInf/vis_layout.py
onetjobsInf/test/test_BFS_search.py
onetjobsInf/test/test_abilities_download.py
onetjobsInf/test/test_linalg_skills.py
onetjobsska-0.1.17.dist-info/licenses/LICENSE
onetjobsska-0.1.17.dist-info/METADATA
onetjobsska-0.1.17.dist-info/WHEEL
onetjobsska-0.1.17.dist-info/top_level.txt
onetjobsska-0.1.17.dist-info/RECORD
