Metadata-Version: 2.4
Name: onetjobsSKA
Version: 0.1.17
Summary: A python package for contrasting and comparing jobs based on skills, knowledge, and abilities, as obtained from the O*NET Database.
Author-email: "P. Nevins" <pnevins@fas.harvard.edu>, "M. Carbonneau" <mcarbonneau@g.harvard.edu>, "H. Jin" <jdoe@example.com>
License: MIT
Project-URL: Homepage, https://github.com/yourusername/job-comparison-dashboard
Keywords: PCA,breadth-first search,job comparison,radar plots,O*NET
Classifier: Programming Language :: Python :: 3
Classifier: License :: OSI Approved :: MIT License
Classifier: Operating System :: OS Independent
Requires-Python: >=3.7
License-File: LICENSE
Requires-Dist: dash>=1.21.0
Requires-Dist: pandas>=1.0.0
Requires-Dist: plotly>=5.0.0
Requires-Dist: requests>=2.0.0
Requires-Dist: werkzeug==2.0.3
Dynamic: license-file
